LICENSE.md
README.md
setup.cfg
setup.py
mitdeeplearning/__init__.py
mitdeeplearning/lab1.py
mitdeeplearning/lab2.py
mitdeeplearning/lab3.py
mitdeeplearning/lab3_old.py
mitdeeplearning/util.py
mitdeeplearning.egg-info/PKG-INFO
mitdeeplearning.egg-info/SOURCES.txt
mitdeeplearning.egg-info/dependency_links.txt
mitdeeplearning.egg-info/requires.txt
mitdeeplearning.egg-info/top_level.txt
mitdeeplearning/bin/abc2wav
mitdeeplearning/data/irish.abc
mitdeeplearning/data/faces/DF/10.png
mitdeeplearning/data/faces/DF/19.png
mitdeeplearning/data/faces/DF/6.png
mitdeeplearning/data/faces/DF/7.png
mitdeeplearning/data/faces/DF/9.png
mitdeeplearning/data/faces/DM/20.png
mitdeeplearning/data/faces/DM/3.png
mitdeeplearning/data/faces/DM/5.png
mitdeeplearning/data/faces/DM/8.png
mitdeeplearning/data/faces/DM/9.png
mitdeeplearning/data/faces/LF/1.png
mitdeeplearning/data/faces/LF/11.png
mitdeeplearning/data/faces/LF/2.png
mitdeeplearning/data/faces/LF/4.png
mitdeeplearning/data/faces/LF/8.png
mitdeeplearning/data/faces/LM/1.png
mitdeeplearning/data/faces/LM/11.png
mitdeeplearning/data/faces/LM/5.png
mitdeeplearning/data/faces/LM/8.png
mitdeeplearning/data/faces/LM/9.png
mitdeeplearning/data/text_styles/leprechaun.txt
mitdeeplearning/data/text_styles/yoda.txt